[
{
    "id": 1,
    "title": "Видавництво Старого Лева",
    "cover": "img/dd4e4f511a21c1c96c284e84e3bc9b906b9d841c.jpeg.webp",
    "genre": "Видвництво"
  },
  {
  "id": 2,
  "title": "Клуб Сімейного Дозвілля",
  "cover": "img/maxresdefault.jpg",
  "genre": "Видавництво",
  "description": "Одне з найбільших українських видавництв, що випускає художню літературу, бестселери та книги для всієї родини."
},
{
  "id": 3,
  "title": "Ранок",
  "cover": "img/c20a75252483f291.jpg",
  "genre": "Видавництво",
  "description": "Популярне українське видавництво, яке спеціалізується на дитячій літературі, підручниках і розвивальних книгах."
},
{
  "id": 4,
  "title": "Фоліо",
  "cover": "img/86bd4d5a1e3027cf93d64ff7267d6eb6.png",
  "genre": "Видавництво",
  "description": "Видавництво з широким асортиментом книг: від класики до сучасної літератури та історичних видань."
},
{
  "id": 5,
  "title": "Наш Формат",
  "cover": "img/logo_nash_format_red_1_.jpg",
  "genre": "Видавництво",
  "description": "Спеціалізується на бізнес-літературі, саморозвитку та книгах про сучасні ідеї та технології."
}
]